setup.py
heheda1/__init__.py
heheda1.egg-info/PKG-INFO
heheda1.egg-info/SOURCES.txt
heheda1.egg-info/dependency_links.txt
heheda1.egg-info/not-zip-safe
heheda1.egg-info/top_level.txt