Metadata-Version: 1.0
Name: heheda1
Version: 0.1
Summary: clinical trial information retriver
Home-page: http://github.com/tongling/clinicaltrial
Author: Ling
Author-email: tonglingacademic@gmail.com
License: MIT
Platform: UNKNOWN
